optess/__init__.py
optess/factories.py
optess/hybridbuilder.py
optess/hybriddia.py
optess/objective.py
optess/optimize_ess.py
optess/results.py
optess/signal.py
optess/singlebuilder.py
optess/storage.py
optess/utility.py
optess-0.1.dist-info/METADATA
optess-0.1.dist-info/RECORD
optess-0.1.dist-info/WHEEL
optess-0.1.dist-info/top_level.txt
