Metadata-Version: 2.1
Name: optess
Version: 0.1
Summary: Find an optimal energy storage system or hybrid energy storage system for a certain load profile
Home-page: http://github.com/s-guenther/optess
Author: Sebastian Günther
Author-email: sebastian.guenther@ifes.uni-hannover.de
License: GPLv3
Platform: UNKNOWN
Requires-Dist: matplotlib
Requires-Dist: pyomo
Requires-Dist: numpy
Requires-Dist: scipy
Requires-Dist: overload
